LICENSE.txt
README.md
pyproject.toml
src/phem.egg-info/PKG-INFO
src/phem.egg-info/SOURCES.txt
src/phem.egg-info/dependency_links.txt
src/phem.egg-info/requires.txt
src/phem.egg-info/top_level.txt
src/phem/application_utils/default_configurations.py
src/phem/application_utils/methods_factories.py
src/phem/application_utils/supported_metrics.py
src/phem/base_utils/diversity_metrics.py
src/phem/base_utils/metrics.py
src/phem/base_utils/preprocessing.py
src/phem/base_utils/custom_metrics/roc_auc.py
src/phem/framework/abstract_ensemble.py
src/phem/framework/abstract_weighted_ensemble.py
src/phem/methods/baselines/__init__.py
src/phem/methods/baselines/single_best.py
src/phem/methods/ensemble_selection/__init__.py
src/phem/methods/ensemble_selection/greedy_ensemble_selection.py
src/phem/methods/ensemble_selection/qdo/__init__.py
src/phem/methods/ensemble_selection/qdo/behavior_space.py
src/phem/methods/ensemble_selection/qdo/behavior_spaces.py
src/phem/methods/ensemble_selection/qdo/emitters.py
src/phem/methods/ensemble_selection/qdo/qdo_es.py
src/phem/methods/ensemble_selection/qdo/behavior_functions/basic.py
src/phem/methods/ensemble_selection/qdo/behavior_functions/implicit_diversity_metrics.py
src/phem/methods/ensemble_selection/qdo/custom_archives/custom_sliding_boundaries_archive.py
src/phem/methods/ensemble_selection/qdo/custom_archives/quality_archive.py
src/phem/methods/ensemble_selection/qdo/custom_archives/utils.py