Metadata-Version: 2.1
Name: phem
Version: 0.0.0.2
Summary: PHEM: A collection of Post Hoc Ensemble Methods for (Auto)ML
Author-email: Lennart Purucker <contact@lennart-purucker.com>
Project-URL: source, https://github.com/LennartPurucker/phem
Project-URL: documentation, https://github.com/LennartPurucker/phem/issues
Classifier: Programming Language :: Python :: 3
Classifier: License :: OSI Approved :: MIT License
Classifier: Operating System :: OS Independent
Requires-Python: >=3.10
License-File: LICENSE.txt
Requires-Dist: typing_extensions
Requires-Dist: more_itertools
Requires-Dist: assembled[openml]==0.0.4
Requires-Dist: ConfigSpace==0.6.1
Requires-Dist: scikit-learn
Requires-Dist: phem[all-methods]
Provides-Extra: dev
Requires-Dist: phem[doc,examples,test,tooling]; extra == "dev"
Provides-Extra: tooling
Requires-Dist: commitizen; extra == "tooling"
Requires-Dist: pre-commit; extra == "tooling"
Requires-Dist: ruff; extra == "tooling"
Requires-Dist: mypy; extra == "tooling"
Requires-Dist: types-psutil; extra == "tooling"
Requires-Dist: types-pyyaml; extra == "tooling"
Provides-Extra: test
Requires-Dist: pytest<8; extra == "test"
Requires-Dist: pytest-coverage; extra == "test"
Requires-Dist: pytest-cases; extra == "test"
Provides-Extra: examples
Requires-Dist: openml; extra == "examples"
Provides-Extra: doc
Requires-Dist: mkdocs; extra == "doc"
Requires-Dist: mkdocs-material; extra == "doc"
Requires-Dist: mkdocs-autorefs; extra == "doc"
Requires-Dist: mkdocs-gen-files; extra == "doc"
Requires-Dist: mkdocs-literate-nav; extra == "doc"
Requires-Dist: mkdocs-glightbox; extra == "doc"
Requires-Dist: mkdocstrings[python]; extra == "doc"
Requires-Dist: markdown-exec[ansi]; extra == "doc"
Requires-Dist: matplotlib; extra == "doc"
Requires-Dist: rich; extra == "doc"
Requires-Dist: mike; extra == "doc"
Requires-Dist: pillow; extra == "doc"
Requires-Dist: cairosvg; extra == "doc"
Requires-Dist: black; extra == "doc"
Provides-Extra: all-methods
Requires-Dist: phem[cmaes,qdoes]; extra == "all-methods"
Provides-Extra: qdoes
Requires-Dist: ribs==0.4.0; extra == "qdoes"
Provides-Extra: cmaes
Requires-Dist: cma==3.2.2; extra == "cmaes"
